pyanis/__init__.py
pyanis/fileops/__init__.py
pyanis/fileops/utils.py
pyanis/vision/__init__.py
pyanis/vision/stickyplate.py
pyanis/vision/utils.py
pyanis-0.1.1.dist-info/LICENSE
pyanis-0.1.1.dist-info/METADATA
pyanis-0.1.1.dist-info/WHEEL
pyanis-0.1.1.dist-info/top_level.txt
pyanis-0.1.1.dist-info/RECORD
