Metadata-Version: 2.1
Name: pyanis
Version: 0.1.1
Summary: Functions and tools I have found useful through the years
Author: Yannis Kalfas
License: UNKNOWN
Platform: UNKNOWN
Requires-Python: >=3.5
License-File: LICENSE
Requires-Dist: pandas
Requires-Dist: matplotlib
Requires-Dist: scikit-learn
Requires-Dist: scipy
Requires-Dist: numpy
Requires-Dist: opencv-contrib-python
Requires-Dist: tqdm
